csvalidate/__init__.py
csvalidate/reader.py
csvalidate/writer.py
csvalidate-1.1.2.dist-info/LICENSE.txt
csvalidate-1.1.2.dist-info/METADATA
csvalidate-1.1.2.dist-info/WHEEL
csvalidate-1.1.2.dist-info/top_level.txt
csvalidate-1.1.2.dist-info/RECORD
