Metadata-Version: 2.1
Name: csvalidate
Version: 1.1.2
Summary: CSV reader and writer with validation
Home-page: https://github.com/Shir0kamii/csvalidate
Download-URL: https://github.com/Shir0kamii/csvalidate/tags
Author: Shir0kamii
Author-email: shir0kamii@gmail.com
Platform: any
Classifier: License :: OSI Approved :: MIT License
Classifier: Programming Language :: Python
Classifier: Programming Language :: Python :: 2.7
Classifier: Programming Language :: Python :: 3.4
Classifier: Programming Language :: Python :: 3.5
License-File: LICENSE.txt
Requires-Dist: marshmallow
